<annotation>
	<folder>images</folder>
	<filename>pos-86.jpg</filename>
	<path>/home/mclovin/Pictures/sign_dataset/images/pos-86.jpg</path>
	<source>
		<database>Unknown</database>
	</source>
	<size>
		<width>300</width>
		<height>300</height>
		<depth>3</depth>
	</size>
	<segmented>0</segmented>
	<object>
		<name>sign</name>
		<pose>Unspecified</pose>
		<truncated>0</truncated>
		<difficult>0</difficult>
		<bndbox>
			<xmin>9</xmin>
			<ymin>19</ymin>
			<xmax>293</xmax>
			<ymax>253</ymax>
		</bndbox>
	</object>
</annotation>
